{
    "version": "1.3.0",
    "architecture": {
        "32bit": {
            "url": "https://github.com/GGP1/kure/releases/download/v1.3.0/kure_v1.3.0_windows_386.zip",
            "bin": [
                "kure.exe"
            ],
            "hash": "f065fc4444d270d9dce2e3ea547ff3da28b6ea34877292a5d7d7d82f34a442df"
        },
        "64bit": {
            "url": "https://github.com/GGP1/kure/releases/download/v1.3.0/kure_v1.3.0_windows_amd64.zip",
            "bin": [
                "kure.exe"
            ],
            "hash": "45540386e601930f8f9f978ef3847717ae5714b99138d9c7d38a6b8823235ce6"
        },
        "arm64": {
            "url": "https://github.com/GGP1/kure/releases/download/v1.3.0/kure_v1.3.0_windows_arm64.zip",
            "bin": [
                "kure.exe"
            ],
            "hash": "00767343b51a74c3b70912caa58506b27e0ca54a9e0321abd2350153a3f12ca8"
        }
    },
    "homepage": "https://github.com/GGP1/kure",
    "license": "Apache 2.0",
    "description": "Cross-platform CLI password manager with sessions"
}
